compas_timber_pb/__init__.py
compas_timber_pb/data.py
compas_timber_pb/planning.py
compas_timber_pb/generated/building_plan_pb2.py
compas_timber_pb/generated/elements_pb2.py
compas_timber_pb/generated/processing_pb2.py
compas_timber_pb-0.2.0.dist-info/licenses/LICENSE
compas_timber_pb-0.2.0.dist-info/METADATA
compas_timber_pb-0.2.0.dist-info/WHEEL
compas_timber_pb-0.2.0.dist-info/entry_points.txt
compas_timber_pb-0.2.0.dist-info/top_level.txt
compas_timber_pb-0.2.0.dist-info/RECORD
