Metadata-Version: 2.4
Name: compas_timber_pb
Version: 0.2.0
Summary: COMPAS Timber protobuf plugin
Author-email: Chen Kasirer <kasirer@arch.ethz.ch>
License: MIT License
Project-URL: Homepage, https://gramaziokohler.github.io/compas_timber_pb
Project-URL: Documentation, https://gramaziokohler.github.io/compas_timber_pb
Project-URL: Repository, https://github.com/gramaziokohler/compas_timber_pb
Project-URL: Changelog, https://github.com/gramaziokohler/compas_timber_pb/blob/main/CHANGELOG.md
Project-URL: Issues, https://github.com/gramaziokohler/compas_timber_pb/issues
Project-URL: Forum, https://forum.compas-framework.org/
Classifier: Development Status :: 4 - Beta
Classifier: Topic :: Scientific/Engineering
Classifier: Operating System :: Unix
Classifier: Operating System :: POSIX
Classifier: Operating System :: Microsoft :: Windows
Classifier: Programming Language :: Python
Classifier: Programming Language :: Python :: 3
Classifier: Programming Language :: Python :: 3.10
Classifier: Programming Language :: Python :: 3.11
Classifier: Programming Language :: Python :: 3.12
Requires-Python: >=3.9
License-File: LICENSE
Requires-Dist: compas_pb>=0.4.0
Requires-Dist: compas_timber
Provides-Extra: dev
Requires-Dist: attrs>=17.4; extra == "dev"
Requires-Dist: black>=22.12.0; extra == "dev"
Requires-Dist: bump-my-version; extra == "dev"
Requires-Dist: compas_invocations2; extra == "dev"
Requires-Dist: invoke>=0.14; extra == "dev"
Requires-Dist: ruff; extra == "dev"
Requires-Dist: sphinx_compas2_theme; extra == "dev"
Requires-Dist: twine; extra == "dev"
Requires-Dist: wheel; extra == "dev"
Requires-Dist: build; extra == "dev"
Dynamic: license-file
